huginn/LDA.py
huginn/__init__.py
huginn/anomalies.py
huginn/articles.py
huginn/exceptions.py
huginn/huginn.py
huginn/interest.py
huginn/summarizer.py
huginn/visualize.py
huginn/config/sections.txt
huginn-0.1.4.dist-info/LICENSE.txt
huginn-0.1.4.dist-info/METADATA
huginn-0.1.4.dist-info/WHEEL
huginn-0.1.4.dist-info/top_level.txt
huginn-0.1.4.dist-info/RECORD
