Metadata-Version: 2.1
Name: huginn
Version: 0.1.4
Summary: Tools to Detect Anomalous Events and News Related to Entities
Home-page: http://github.com/tcausero/huginn
Author: Jesse Cahill, Thomas Causero, James DeAntonis, Ryan McNally
Author-email: jcahill225@gmail.com, tc3030@columbia.edu, jad2295@columbia.edu, rom2109@columbia.edu
License: MIT
Platform: UNKNOWN
Requires-Python: >=3.5, <3.7
Requires-Dist: pandas
Requires-Dist: matplotlib
Requires-Dist: pytrends
Requires-Dist: geopandas
Requires-Dist: scikit-learn
Requires-Dist: colour
Requires-Dist: numpy
Requires-Dist: click
Requires-Dist: bs4
Requires-Dist: plotly
Requires-Dist: pyLDAvis
Requires-Dist: gensim
Requires-Dist: tokenizer
Requires-Dist: spacy
Requires-Dist: nltk
Requires-Dist: torch
Requires-Dist: transformers
